setup.cfg
setup.py
ssvepy/__init__.py
ssvepy/exampledata.py
ssvepy/frequencymaths.py
ssvepy/predictstates.py
ssvepy/ssvepyepochs.py
ssvepy.egg-info/PKG-INFO
ssvepy.egg-info/SOURCES.txt
ssvepy.egg-info/dependency_links.txt
ssvepy.egg-info/requires.txt
ssvepy.egg-info/top_level.txt
ssvepy/exampledata/example-epo.fif