Metadata-Version: 1.1
Name: ssvepy
Version: 0.2
Summary: A package that provides classes for SSVEP analysis
Home-page: https://www.janfreyberg.com/ssvepy/
Author: Jan Freyberg
Author-email: jan.freyberg@gmail.com
License: UNKNOWN
Download-URL: https://github.com/janfreyberg/ssvepy/0.2
Platform: UNKNOWN
